randomnipple/MainWindow.py
randomnipple/NippleOptionDict.py
randomnipple/RandomPlayer.py
randomnipple/VoiceDirectoryChecker.py
randomnipple/__init__.py
randomnipple/main.py
randomnipple/py.typed
random_nipple_player-1.5.dist-info/LICENSE
random_nipple_player-1.5.dist-info/METADATA
random_nipple_player-1.5.dist-info/WHEEL
random_nipple_player-1.5.dist-info/entry_points.txt
random_nipple_player-1.5.dist-info/top_level.txt
random_nipple_player-1.5.dist-info/RECORD
