Metadata-Version: 2.1
Name: random-nipple-player
Version: 1.5
Summary: 音声作品「乳首オナ指示でカリカリタイム」(RJ323807)用のプレイヤー
Home-page: https://github.com/eggplants/random-nipple-player
Author: eggplants
Author-email: w10776e8w@yahoo.co.jp
License: MIT
Platform: UNKNOWN
Classifier: License :: OSI Approved :: MIT License
Classifier: Programming Language :: Python
Classifier: Programming Language :: Python :: 3
Classifier: Programming Language :: Python :: 3.8
Classifier: Programming Language :: Python :: 3.9
Classifier: Programming Language :: Python :: 3.10
Classifier: Programming Language :: Python :: Implementation :: CPython
Requires-Python: >=3.8
License-File: LICENSE
Requires-Dist: PySimpleGUI (>=4.57.0)
Requires-Dist: simpleaudio (>=1.0.4)
Provides-Extra: dev
Requires-Dist: black ; extra == 'dev'
Requires-Dist: flake8 ; extra == 'dev'
Requires-Dist: mypy ; extra == 'dev'
Requires-Dist: setuptools (>=46.4.0) ; extra == 'dev'
Requires-Dist: types-requests ; extra == 'dev'
